[
    {
        "timestamp": "2025-06-30 20:08:33",
        "type": "WARNING",
        "message": "取得したデータが空です。スキップします。"
    },
    {
        "timestamp": "2025-06-30 20:08:34",
        "type": "WARNING",
        "message": "取得したデータが空です。スキップします。"
    },
    {
        "timestamp": "2025-06-30 20:08:34",
        "type": "WARNING",
        "message": "取得したデータが空です。スキップします。"
    },
    {
        "timestamp": "2025-06-30 20:08:34",
        "type": "WARNING",
        "message": "取得したデータが空です。スキップします。"
    },
    {
        "timestamp": "2025-06-30 20:08:35",
        "type": "WARNING",
        "message": "取得したデータが空です。スキップします。"
    },
    {
        "timestamp": "2025-06-30 20:09:15",
        "type": "WARNING",
        "message": "取得したデータが空です。スキップします。"
    },
    {
        "timestamp": "2025-06-30 20:10:16",
        "type": "WARNING",
        "message": "取得したデータが空です。スキップします。"
    },
    {
        "timestamp": "2025-06-30 20:11:18",
        "type": "WARNING",
        "message": "取得したデータが空です。スキップします。"
    },
    {
        "timestamp": "2025-06-30 20:12:18",
        "type": "WARNING",
        "message": "取得したデータが空です。スキップします。"
    },
    {
        "timestamp": "2025-06-30 20:13:15",
        "type": "WARNING",
        "message": "取得したデータが空です。スキップします。"
    },
    {
        "timestamp": "2025-06-30 20:13:21",
        "type": "WARNING",
        "message": "取得したデータが空です。スキップします。"
    },
    {
        "timestamp": "2025-06-30 20:14:18",
        "type": "WARNING",
        "message": "取得したデータが空です。スキップします。"
    },
    {
        "timestamp": "2025-06-30 20:15:19",
        "type": "WARNING",
        "message": "取得したデータが空です。スキップします。"
    },
    {
        "timestamp": "2025-06-30 20:16:20",
        "type": "WARNING",
        "message": "取得したデータが空です。スキップします。"
    },
    {
        "timestamp": "2025-06-30 20:17:20",
        "type": "WARNING",
        "message": "取得したデータが空です。スキップします。"
    }
]